[[{"label": "Id", "value": "dc00106273"}, {"isTitle": true, "value": "Eine Kanne aus Muschelwerk"}, {"isImage": true, "value": "https://manducus.net/mkgcs/proxy.php?url=http://resources.digicult-museen.net/dam/provided_image/m58c1f311edbbe"}, {"label": "Open Website", "isLink": true, "value": "http://sammlungonline.mkg-hamburg.de/de/object/Eine+Kanne+aus+Muschelwerk/O1909.82/dc00106273"}, {"label": "Inventarnummer", "value": "O1909.82"}, {"label": "Sachgruppe", "value": "Druckgrafik/Druckerzeugnisse"}, {"label": "Jahr", "value": "1745"}, {"label": "Ort", "value": "Augsburg "}], [{"label": "Id", "value": "dc00106274"}, {"isTitle": true, "value": "Eine Kanne aus Muschelwerk"}, {"isImage": true, "value": "https://manducus.net/mkgcs/proxy.php?url=http://resources.digicult-museen.net/dam/provided_image/m58c1f313a1460"}, {"label": "Open Website", "isLink": true, "value": "http://sammlungonline.mkg-hamburg.de/de/object/Eine+Kanne+aus+Muschelwerk/O1909.83/dc00106274"}, {"label": "Inventarnummer", "value": "O1909.83"}, {"label": "Sachgruppe", "value": "Druckgrafik/Druckerzeugnisse"}, {"label": "Jahr", "value": "1745"}, {"label": "Ort", "value": "Augsburg "}], [{"label": "Id", "value": "dc00106275"}, {"isTitle": true, "value": "Eine Kanne aus Muschelwerk"}, {"isImage": true, "value": "https://manducus.net/mkgcs/proxy.php?url=http://resources.digicult-museen.net/dam/provided_image/m58c1f3153a06f"}, {"label": "Open Website", "isLink": true, "value": "http://sammlungonline.mkg-hamburg.de/de/object/Eine+Kanne+aus+Muschelwerk/O1909.84/dc00106275"}, {"label": "Inventarnummer", "value": "O1909.84"}, {"label": "Sachgruppe", "value": "Druckgrafik/Druckerzeugnisse"}, {"label": "Jahr", "value": "1745"}, {"label": "Ort", "value": "Augsburg "}], [{"label": "Id", "value": "dc00106276"}, {"isTitle": true, "value": "Eine Kanne aus Muschelwerk"}, {"isImage": true, "value": "https://manducus.net/mkgcs/proxy.php?url=http://resources.digicult-museen.net/dam/provided_image/m58c1f316da5b2"}, {"label": "Open Website", "isLink": true, "value": "http://sammlungonline.mkg-hamburg.de/de/object/Eine+Kanne+aus+Muschelwerk/O1909.85/dc00106276"}, {"label": "Inventarnummer", "value": "O1909.85"}, {"label": "Sachgruppe", "value": "Druckgrafik/Druckerzeugnisse"}, {"label": "Jahr", "value": "1745"}, {"label": "Ort", "value": "Augsburg "}], [{"label": "Id", "value": "dc00106282"}, {"isTitle": true, "value": "Dosen"}, {"isImage": true, "value": "https://manducus.net/mkgcs/proxy.php?url=http://resources.digicult-museen.net/dam/provided_image/m58c1f3186fe9b"}, {"label": "Open Website", "isLink": true, "value": "http://sammlungonline.mkg-hamburg.de/de/object/Dosen/O1911.47/dc00106282"}, {"label": "Inventarnummer", "value": "O1911.47"}, {"label": "Sachgruppe", "value": "Druckgrafik/Druckerzeugnisse"}, {"label": "Jahr", "value": "1745"}, {"label": "Ort", "value": "Augsburg "}], [{"label": "Id", "value": "dc00106283"}, {"isTitle": true, "value": "Dosendeckel und Stockkn\u00e4ufe"}, {"isImage": true, "value": "https://manducus.net/mkgcs/proxy.php?url=http://resources.digicult-museen.net/dam/provided_image/m58c1f31a22729"}, {"label": "Open Website", "isLink": true, "value": "http://sammlungonline.mkg-hamburg.de/de/object/Dosendeckel+und+Stockkn%C3%A4ufe/O1911.48/dc00106283"}, {"label": "Inventarnummer", "value": "O1911.48"}, {"label": "Sachgruppe", "value": "Druckgrafik/Druckerzeugnisse"}, {"label": "Jahr", "value": "1745"}, {"label": "Ort", "value": "Augsburg "}], [{"label": "Id", "value": "dc00106284"}, {"isTitle": true, "value": "Deckeldosen; Pokal und Rahmen"}, {"isImage": true, "value": "https://manducus.net/mkgcs/proxy.php?url=http://resources.digicult-museen.net/dam/provided_image/m58c1f31bc1667"}, {"label": "Open Website", "isLink": true, "value": "http://sammlungonline.mkg-hamburg.de/de/object/Deckeldosen%2C+Pokal+und+Rahmen/O1911.49/dc00106284"}, {"label": "Inventarnummer", "value": "O1911.49"}, {"label": "Sachgruppe", "value": "Druckgrafik/Druckerzeugnisse"}, {"label": "Jahr", "value": "1745"}, {"label": "Ort", "value": "Augsburg "}], [{"label": "Id", "value": "dc00106285"}, {"isTitle": true, "value": "Deckeldosen; Schale und Stockknauf"}, {"isImage": true, "value": "https://manducus.net/mkgcs/proxy.php?url=http://resources.digicult-museen.net/dam/provided_image/m58c1f31d66b82"}, {"label": "Open Website", "isLink": true, "value": "http://sammlungonline.mkg-hamburg.de/de/object/Deckeldosen%2C+Schale+und+Stockknauf/O1911.50/dc00106285"}, {"label": "Inventarnummer", "value": "O1911.50"}, {"label": "Sachgruppe", "value": "Druckgrafik/Druckerzeugnisse"}, {"label": "Jahr", "value": "1745"}, {"label": "Ort", "value": "Augsburg "}], [{"label": "Id", "value": "dc00106286"}, {"isTitle": true, "value": "Wandleuchter aus Muschelwerk mit mythologischer Szene"}, {"isImage": true, "value": "https://manducus.net/mkgcs/proxy.php?url=http://resources.digicult-museen.net/dam/provided_image/m59cfa15c1959a"}, {"label": "Open Website", "isLink": true, "value": "http://sammlungonline.mkg-hamburg.de/de/object/Wandleuchter+aus+Muschelwerk+mit+mythologischer+Szene/O1913.304/dc00106286"}, {"label": "Inventarnummer", "value": "O1913.304"}, {"label": "Sachgruppe", "value": "Druckgrafik/Druckerzeugnisse"}, {"label": "Jahr", "value": "1745"}, {"label": "Ort", "value": "Augsburg "}]]