[[{"label": "Id", "value": "dc00117966"}, {"isTitle": true, "value": "Der Schauspieler Ichikawa Danj\u016br\u014d IV"}, {"isImage": true, "value": "https://manducus.net/mkgcs/proxy.php?url=http://resources.digicult-museen.net/dam/provided_image/m57d2f72a09027"}, {"label": "Open Website", "isLink": true, "value": "http://sammlungonline.mkg-hamburg.de/de/object/Der+Schauspieler+Ichikawa+Danj%C5%ABr%C5%8D+IV/IE1903.4/dc00117966"}, {"label": "Sammlung", "value": "Ostasien"}, {"label": "Inventarnummer", "value": "IE1903.4"}, {"label": "Sachgruppe", "value": "Druckgrafik/Druckerzeugnisse"}, {"label": "Jahr", "value": "1768"}, {"label": "Ort", "value": "Tokio "}], [{"label": "Id", "value": "dc00117967"}, {"isTitle": true, "value": "Der Schauspieler Onoe Baik\u014d IV als Ch\u016br\u014d Onoe in einer Szene des zweiten Akts der Kabuki-Auff\u00fchrung Hanato Mimasu yayoi no Hatsuyaku"}, {"isImage": true, "value": "https://manducus.net/mkgcs/proxy.php?url=http://resources.digicult-museen.net/dam/provided_image/m57d2f72a9ccb8"}, {"label": "Open Website", "isLink": true, "value": "http://sammlungonline.mkg-hamburg.de/de/object/Schauspieler+Onoe+Baik%C5%8D+IV+%28%E5%9B%9B%E4%BB%A3%E7%9B%AE%E5%B0%BE%E4%B8%8A%E6%A2%85%E5%B9%B8%29+als+Ch%C5%ABr%C5%8D+Onoe+%28%E4%B8%AD%E8%80%81%E5%B0%BE%E4%B8%8A%29+in+einer+Szene+des+zweiten+Akts+der+Kabuki-Auff%C3%BChrung+Hanato+Mimasu+yayoi+no+Hatsuyaku/1985.220/dc00117967"}, {"label": "Sammlung", "value": "Ostasien"}, {"label": "Inventarnummer", "value": "1985.22"}, {"label": "Sachgruppe", "value": "Druckgrafik/Druckerzeugnisse"}, {"label": "Jahr", "value": "1768"}, {"label": "Ort", "value": "Tokio "}], [{"label": "Id", "value": "dc00117969"}, {"isTitle": true, "value": "Junge Dame mit Dienerin im Schnee"}, {"isImage": true, "value": "https://manducus.net/mkgcs/proxy.php?url=http://resources.digicult-museen.net/dam/provided_image/m57d2f72b57019"}, {"label": "Open Website", "isLink": true, "value": "http://sammlungonline.mkg-hamburg.de/de/object/Junge+Dame+mit+Dienerin+im+Schnee/IE1969.199/dc00117969"}, {"label": "Sammlung", "value": "Ostasien"}, {"label": "Inventarnummer", "value": "IE1969.199"}, {"label": "Sachgruppe", "value": "Druckgrafik/Druckerzeugnisse"}, {"label": "Jahr", "value": "1768"}, {"label": "Ort", "value": "Tokio "}], [{"label": "Id", "value": "dc00117970"}, {"isTitle": true, "value": "Die Schauspieler Arashi Ry\u016bz\u014d und Ichikawa Komaz\u014d im Schwertkampf"}, {"isImage": true, "value": "https://manducus.net/mkgcs/proxy.php?url=http://resources.digicult-museen.net/dam/provided_image/m57d2f72c07a01"}, {"label": "Open Website", "isLink": true, "value": "http://sammlungonline.mkg-hamburg.de/de/object/Die+Schauspieler+Arashi+Ry%C5%ABz%C5%8D+und+Ichikawa+Komaz%C5%8D+im+Schwertkampf/IE1903.2/dc00117970"}, {"label": "Sammlung", "value": "Ostasien"}, {"label": "Inventarnummer", "value": "IE1903.2"}, {"label": "Sachgruppe", "value": "Druckgrafik/Druckerzeugnisse"}, {"label": "Jahr", "value": "1768"}, {"label": "Ort", "value": "Tokio "}], [{"label": "Id", "value": "dc00117971"}, {"isTitle": true, "value": "Hinamatsuri; Blatt 2 aus der Serie Die f\u00fcnf Feste"}, {"isImage": true, "value": "https://manducus.net/mkgcs/proxy.php?url=http://resources.digicult-museen.net/dam/provided_image/m57d2f72cd9568"}, {"label": "Open Website", "isLink": true, "value": "http://sammlungonline.mkg-hamburg.de/de/object/Hinamatsuri+%28%E9%9B%9B%E7%A5%AD%29%2C+Blatt+2+aus+der+Serie%3A+Die+f%C3%BCnf+Feste+%28Gosekku+%E4%BA%94%E7%AF%80%E5%8F%A5%29+/IE1907.52/dc00117971"}, {"label": "Sammlung", "value": "Ostasien"}, {"label": "Inventarnummer", "value": "IE1907.52"}, {"label": "Sachgruppe", "value": "Druckgrafik/Druckerzeugnisse"}, {"label": "Jahr", "value": "1780"}, {"label": "Ort", "value": "Tokio "}], [{"label": "Id", "value": "dc00117972"}, {"isTitle": true, "value": "Kirschbl\u00fcten in Arashiyama "}, {"isImage": true, "value": "https://manducus.net/mkgcs/proxy.php?url=http://resources.digicult-museen.net/dam/provided_image/m57d2f72d97f4a"}, {"label": "Open Website", "isLink": true, "value": "http://sammlungonline.mkg-hamburg.de/de/object/Kirschbl%C3%BCten+in+Arashiyama+%28Arashiyama+sakura+%E3%81%82%E3%82%89%E3%81%97%E5%B1%B1%E3%81%95%E3%81%8F%E3%82%89%29/IE1897.68/dc00117972"}, {"label": "Sammlung", "value": "Ostasien"}, {"label": "Inventarnummer", "value": "IE1897.68"}, {"label": "Sachgruppe", "value": "Druckgrafik/Druckerzeugnisse"}, {"label": "Jahr", "value": "1780"}, {"label": "Ort", "value": "Tokio "}], [{"label": "Id", "value": "dc00117973"}, {"isTitle": true, "value": "Der Steckenpferdtanz harugoma"}, {"isImage": true, "value": "https://manducus.net/mkgcs/proxy.php?url=http://resources.digicult-museen.net/dam/provided_image/m57d2f72e5a701"}, {"label": "Open Website", "isLink": true, "value": "http://sammlungonline.mkg-hamburg.de/de/object/Der+Steckenpferdtanz+harugoma/IE1908.3/dc00117973"}, {"label": "Sammlung", "value": "Ostasien"}, {"label": "Inventarnummer", "value": "IE1908.3"}, {"label": "Sachgruppe", "value": "Druckgrafik/Druckerzeugnisse"}, {"label": "Jahr", "value": "1780"}, {"label": "Ort", "value": "Tokio "}], [{"label": "Id", "value": "dc00117974"}, {"isTitle": true, "value": "Bild von Menschen aus Nanking; aus dem Buch Bilder importierter V\u00f6gel "}, {"isImage": true, "value": "https://manducus.net/mkgcs/proxy.php?url=http://resources.digicult-museen.net/dam/provided_image/m57d2f72f22050"}, {"label": "Open Website", "isLink": true, "value": "http://sammlungonline.mkg-hamburg.de/de/object/Bild+von+Menschen+aus+Nanking+%28nankinjin+zu+%E5%8D%97%E4%BA%AC%E4%BA%BA%E5%9B%B3%29%2C+aus+dem+Buch%3A+Bilder+importierter+V%C3%B6gel+%28Raikin+zui+%E6%9D%A5%E7%A6%BD%E5%9B%B3%E5%BD%99%29/IE1896.377/dc00117974"}, {"label": "Sammlung", "value": "Ostasien"}, {"label": "Inventarnummer", "value": "IE1896.377"}, {"label": "Sachgruppe", "value": "Druckgrafik/Druckerzeugnisse"}, {"label": "Jahr", "value": "1780"}, {"label": "Ort", "value": "Tokio "}], [{"label": "Id", "value": "dc00117975"}, {"isTitle": true, "value": "Guabich\u014d auf einem bl\u00fchenden Kirschbaumast; aus dem Buch Bilder importierter V\u00f6gel"}, {"isImage": true, "value": "https://manducus.net/mkgcs/proxy.php?url=http://resources.digicult-museen.net/dam/provided_image/m57d2f730a2dd4"}, {"label": "Open Website", "isLink": true, "value": "http://sammlungonline.mkg-hamburg.de/de/object/Guabich%C5%8D+auf+einer+bl%C3%BChenden+Kirschbaumast.%2C+aus+dem+Buch%3A+Bilder+importierter+V%C3%B6gel+%28Raikin+zui+%E6%9D%A5%E7%A6%BD%E5%9B%B3%E5%BD%99%29/IE1896.380/dc00117975"}, {"label": "Sammlung", "value": "Ostasien"}, {"label": "Inventarnummer", "value": "IE1896.380"}, {"label": "Sachgruppe", "value": "Druckgrafik/Druckerzeugnisse"}, {"label": "Jahr", "value": "1780"}, {"label": "Ort", "value": "Tokio "}]]