[[{"label": "Id", "value": "dc00117986"}, {"isTitle": true, "value": "Elegante Frauen aus dem Shikisanban"}, {"isImage": true, "value": "https://manducus.net/mkgcs/proxy.php?url=http://resources.digicult-museen.net/dam/provided_image/m57d2f7384318f"}, {"label": "Sachgruppe", "value": "Druckgrafik/Druckerzeugnisse"}, {"label": "Jahr", "value": "1856"}, {"label": "Ort", "value": "Tokio "}], [{"label": "Id", "value": "dc00117987"}, {"isTitle": true, "value": "Negishi; aus der Serie 100 Sch\u00f6nheiten in ber\u00fchmten Orten in Edo"}, {"isImage": true, "value": "https://manducus.net/mkgcs/proxy.php?url=http://resources.digicult-museen.net/dam/provided_image/m57d2f738e57b5"}, {"label": "Sachgruppe", "value": "Druckgrafik/Druckerzeugnisse"}, {"label": "Jahr", "value": "1856"}, {"label": "Ort", "value": "Tokio "}], [{"label": "Id", "value": "dc00117988"}, {"isTitle": true, "value": "Kamigaike; aus der Serie 100 Sch\u00f6nheiten in ber\u00fchmten Orten in Edo"}, {"isImage": true, "value": "https://manducus.net/mkgcs/proxy.php?url=http://resources.digicult-museen.net/dam/provided_image/m57d2f739ac75d"}, {"label": "Sachgruppe", "value": "Druckgrafik/Druckerzeugnisse"}, {"label": "Jahr", "value": "1856"}, {"label": "Ort", "value": "Tokio "}], [{"label": "Id", "value": "dc00117989"}, {"isTitle": true, "value": "Tatekawa; aus der Serie 100 Sch\u00f6nheiten in ber\u00fchmten Orten in Edo"}, {"isImage": true, "value": "https://manducus.net/mkgcs/proxy.php?url=http://resources.digicult-museen.net/dam/provided_image/m57d2f73a61342"}, {"label": "Sachgruppe", "value": "Druckgrafik/Druckerzeugnisse"}, {"label": "Jahr", "value": "1856"}, {"label": "Ort", "value": "Tokio "}], [{"label": "Id", "value": "dc00117990"}, {"isTitle": true, "value": "Somei; aus der Serie 100 Sch\u00f6nheiten in ber\u00fchmten Orten in Edo"}, {"isImage": true, "value": "https://manducus.net/mkgcs/proxy.php?url=http://resources.digicult-museen.net/dam/provided_image/m57d2f73b216b3"}, {"label": "Sachgruppe", "value": "Druckgrafik/Druckerzeugnisse"}, {"label": "Jahr", "value": "1856"}, {"label": "Ort", "value": "Tokio "}], [{"label": "Id", "value": "dc00117991"}, {"isTitle": true, "value": "Mokubo-ji; aus der Serie 100 Sch\u00f6nheiten in ber\u00fchmten Orten in Edo"}, {"isImage": true, "value": "https://manducus.net/mkgcs/proxy.php?url=http://resources.digicult-museen.net/dam/provided_image/m57d2f73bc8ecb"}, {"label": "Sachgruppe", "value": "Druckgrafik/Druckerzeugnisse"}, {"label": "Jahr", "value": "1857"}, {"label": "Ort", "value": "Tokio "}], [{"label": "Id", "value": "dc00117992"}, {"isTitle": true, "value": "\u014cji Inari-Schrein; aus der Serie 100 Sch\u00f6nheiten in ber\u00fchmten Orten in Edo"}, {"isImage": true, "value": "https://manducus.net/mkgcs/proxy.php?url=http://resources.digicult-museen.net/dam/provided_image/m57d2f73c76e9b"}, {"label": "Sachgruppe", "value": "Druckgrafik/Druckerzeugnisse"}, {"label": "Jahr", "value": "1857"}, {"label": "Ort", "value": "Tokio "}], [{"label": "Id", "value": "dc00117993"}, {"isTitle": true, "value": "\u014ckawabashi; lokale Bezeichnung Azumabashi; aus der Serie 100 Sch\u00f6nheiten in ber\u00fchmten Orten in Edo"}, {"isImage": true, "value": "https://manducus.net/mkgcs/proxy.php?url=http://resources.digicult-museen.net/dam/provided_image/m57d2f73d2601c"}, {"label": "Sachgruppe", "value": "Druckgrafik/Druckerzeugnisse"}, {"label": "Jahr", "value": "1857"}, {"label": "Ort", "value": "Tokio "}], [{"label": "Id", "value": "dc00117994"}, {"isTitle": true, "value": "Nihonbashi; aus der Serie 100 Sch\u00f6nheiten in ber\u00fchmten Orten in Edo"}, {"isImage": true, "value": "https://manducus.net/mkgcs/proxy.php?url=http://resources.digicult-museen.net/dam/provided_image/m57d2f73de0a9d"}, {"label": "Sachgruppe", "value": "Druckgrafik/Druckerzeugnisse"}, {"label": "Jahr", "value": "1857"}, {"label": "Ort", "value": "Tokio "}], [{"label": "Id", "value": "dc00117995"}, {"isTitle": true, "value": "Vor dem Daion-ji; aus der Serie 100 Sch\u00f6nheiten in ber\u00fchmten Orten in Edo"}, {"isImage": true, "value": "https://manducus.net/mkgcs/proxy.php?url=http://resources.digicult-museen.net/dam/provided_image/m57d2f73e9dbef"}, {"label": "Sachgruppe", "value": "Druckgrafik/Druckerzeugnisse"}, {"label": "Jahr", "value": "1857"}, {"label": "Ort", "value": "Tokio "}]]