[[{"isTitle": true, "value": "Jacob S\u00fcberkr\u00fcb (geb. 1766)"}, {"label": "Hersteller*in/K\u00fcnstler*in", "value": "Unbekannt (Fotograf/in)"}, {"label": "Ort", "value": "Deutschland "}, {"label": "Jahr", "value": "1840"}, {"label": "Sachgruppe", "value": "Portr\u00e4tfotografie"}, {"label": "Sammlung", "value": "Fotografie und neue Medien"}, {"label": "Inventarnummer", "value": "PD1915.231"}, {"label": "Zum Objekt", "isLink": true, "value": "http://sammlungonline.mkg-hamburg.de/de/object/Jacob+S%C3%BCberkr%C3%BCb+%28geb.+1766%29/PD1915.231/dc00034720"}, {"isImage": true, "value": "https://manducus.net/mkgcs/proxy.php?url=http://resources.digicult-museen.net/dam/provided_image/m57d2ed65ab9ec"}], [{"isTitle": true, "value": "Henriette Br\u00f6dermann; um 1847"}, {"label": "Hersteller*in/K\u00fcnstler*in", "value": "Stelzner&#44; Carl Ferdinand (Fotograf/in)"}, {"label": "Ort", "value": "Deutschland "}, {"label": "Jahr", "value": "1842"}, {"label": "Sachgruppe", "value": "Portr\u00e4tfotografie"}, {"label": "Sammlung", "value": "Fotografie und neue Medien"}, {"label": "Inventarnummer", "value": "PD1915.232"}, {"label": "Zum Objekt", "isLink": true, "value": "http://sammlungonline.mkg-hamburg.de/de/object/Henriette+Br%C3%B6dermann%2C+um+1847/PD1915.232/dc00034721"}, {"isImage": true, "value": "https://manducus.net/mkgcs/proxy.php?url=http://resources.digicult-museen.net/dam/provided_image/m57d2ed665379d"}], [{"isTitle": true, "value": "Ernst Greve"}, {"label": "Hersteller*in/K\u00fcnstler*in", "value": "Breuning&#44; Wilhelm (Fotograf/in)"}, {"label": "Ort", "value": "Hamburg "}, {"label": "Jahr", "value": "1850"}, {"label": "Sachgruppe", "value": "Portr\u00e4tfotografie"}, {"label": "Sammlung", "value": "Fotografie und neue Medien"}, {"label": "Inventarnummer", "value": "PD1915.244"}, {"label": "Zum Objekt", "isLink": true, "value": "http://sammlungonline.mkg-hamburg.de/de/object/Ernst+Greve/PD1915.244/dc00034722"}, {"isImage": true, "value": "https://manducus.net/mkgcs/proxy.php?url=http://resources.digicult-museen.net/dam/provided_image/m57d2ed66ee806"}], [{"isTitle": true, "value": "Johann P.L. Bartels mit seiner Frau Pauline; geb. Marschner und ihren sieben Kindern"}, {"label": "Hersteller*in/K\u00fcnstler*in", "value": "Stelzner&#44; Carl Ferdinand (Fotograf/in)"}, {"label": "Ort", "value": "Hamburg "}, {"label": "Jahr", "value": "1843"}, {"label": "Sachgruppe", "value": "Portr\u00e4tfotografie"}, {"label": "Sammlung", "value": "Fotografie und neue Medien"}, {"label": "Inventarnummer", "value": "PD1915.245"}, {"label": "Zum Objekt", "isLink": true, "value": "http://sammlungonline.mkg-hamburg.de/de/object/Johann+P.L.+Bartels+mit+seiner+Frau+Pauline%2C+geb.+Marschner+und+ihren+sieben+Kindern/PD1915.245/dc00034723"}, {"isImage": true, "value": "https://manducus.net/mkgcs/proxy.php?url=http://resources.digicult-museen.net/dam/provided_image/m57d2ed67d0816"}], [{"isTitle": true, "value": "Fr. K\u00f6hler und seine Frau; geb. Oelreich"}, {"label": "Hersteller*in/K\u00fcnstler*in", "value": "Unbekannt (Fotograf/in)"}, {"label": "Ort", "value": "Deutschland "}, {"label": "Jahr", "value": "1840"}, {"label": "Sachgruppe", "value": "Portr\u00e4tfotografie"}, {"label": "Sammlung", "value": "Fotografie und neue Medien"}, {"label": "Inventarnummer", "value": "PD1915.249"}, {"label": "Zum Objekt", "isLink": true, "value": "http://sammlungonline.mkg-hamburg.de/de/object/Fr.+K%C3%B6hler+und+seine+Frau%2C+geb.+Oelreich/PD1915.249/dc00034725"}, {"isImage": true, "value": "https://manducus.net/mkgcs/proxy.php?url=http://resources.digicult-museen.net/dam/provided_image/m57d2ed694175c"}], [{"isTitle": true, "value": "Unbekannte Frau"}, {"label": "Hersteller*in/K\u00fcnstler*in", "value": "Unbekannt (Fotograf/in)"}, {"label": "Ort", "value": "Deutschland "}, {"label": "Jahr", "value": "1850"}, {"label": "Sachgruppe", "value": "Portr\u00e4tfotografie"}, {"label": "Sammlung", "value": "Fotografie und neue Medien"}, {"label": "Inventarnummer", "value": "PD1915.251"}, {"label": "Zum Objekt", "isLink": true, "value": "http://sammlungonline.mkg-hamburg.de/de/object/Unbekannte+Frau/PD1915.251/dc00034726"}, {"isImage": true, "value": "https://manducus.net/mkgcs/proxy.php?url=http://resources.digicult-museen.net/dam/provided_image/m57d2ed69cf7dc"}], [{"isTitle": true, "value": "Hinrich Otto de la Camp und seine Braut Mathilde Strantzen"}, {"label": "Hersteller*in/K\u00fcnstler*in", "value": "Biow&#44; Hermann (Fotograf/in)"}, {"label": "Ort", "value": "Hamburg "}, {"label": "Jahr", "value": "1845"}, {"label": "Sachgruppe", "value": "Portr\u00e4tfotografie"}, {"label": "Sammlung", "value": "Fotografie und neue Medien"}, {"label": "Inventarnummer", "value": "PD1915.291"}, {"label": "Zum Objekt", "isLink": true, "value": "http://sammlungonline.mkg-hamburg.de/de/object/Hinrich+Otto+de+la+Camp+und+seine+Braut+Mathilde+Strantzen/PD1915.291/dc00034728"}, {"isImage": true, "value": "https://manducus.net/mkgcs/proxy.php?url=http://resources.digicult-museen.net/dam/provided_image/m59cf7a2f68ac1"}], [{"isTitle": true, "value": "Molly Busse; geb. Merck (1812-1897); 1843"}, {"label": "Hersteller*in/K\u00fcnstler*in", "value": "Stelzner&#44; Carl Ferdinand (Fotograf/in)"}, {"label": "Ort", "value": "Hamburg "}, {"label": "Jahr", "value": "1843"}, {"label": "Sachgruppe", "value": "Portr\u00e4tfotografie"}, {"label": "Sammlung", "value": "Fotografie und neue Medien"}, {"label": "Inventarnummer", "value": "PD1915.292"}, {"label": "Zum Objekt", "isLink": true, "value": "http://sammlungonline.mkg-hamburg.de/de/object/Molly+Busse%2C+geb.+Merck+%281812-1897%29%2C+1843/PD1915.292/dc00034729"}, {"isImage": true, "value": "https://manducus.net/mkgcs/proxy.php?url=http://resources.digicult-museen.net/dam/provided_image/m57d2ed6bb1970"}], [{"isTitle": true, "value": "Molly Busse; geb. Merck (1812-1897)"}, {"label": "Hersteller*in/K\u00fcnstler*in", "value": "Unbekannt (Fotograf/in)"}, {"label": "Ort", "value": "Deutschland "}, {"label": "Jahr", "value": "1858"}, {"label": "Sachgruppe", "value": "Reproduktionsfotografie"}, {"label": "Sammlung", "value": "Fotografie und neue Medien"}, {"label": "Inventarnummer", "value": "PD1915.293"}, {"label": "Zum Objekt", "isLink": true, "value": "http://sammlungonline.mkg-hamburg.de/de/object/Molly+Busse%2C+geb.+Merck+%281812-1897%29/PD1915.293/dc00034730"}, {"isImage": true, "value": "https://manducus.net/mkgcs/proxy.php?url=http://resources.digicult-museen.net/dam/provided_image/m57d2ed6c4abcd"}], [{"isTitle": true, "value": "Tanzauff\u00fchrung in russischer Tracht zur Hochzeit von Johann Heinrich Fixsen und Marie; geb. Hildebrandt. v.l. Gustav Bartels; Hermann Bartels; Alexander L\u00fcders; Marie Bartels; Adolph Bartels"}, {"label": "Hersteller*in/K\u00fcnstler*in", "value": "V\u00f6llner&#44; Johann Anton (Fotograf/in)"}, {"label": "Ort", "value": "Hamburg "}, {"label": "Jahr", "value": "1853"}, {"label": "Sachgruppe", "value": "Portr\u00e4tfotografie"}, {"label": "Sammlung", "value": "Fotografie und neue Medien"}, {"label": "Inventarnummer", "value": "PD1915.294"}, {"label": "Zum Objekt", "isLink": true, "value": "http://sammlungonline.mkg-hamburg.de/de/object/Tanzauff%C3%BChrung+in+russischer+Tracht+zur+Hochzeit+von+Johann+Heinrich+Fixsen+und+Marie%2C+geb.+Hildebrandt.+v.l.%3A+Gustav+Bartels%2C+Hermann+Bartels%2C+Alexander+L%C3%BCders%2C+Marie+Bartels%2C+Adolph+Bartels/PD1915.294/dc00034731"}, {"isImage": true, "value": "https://manducus.net/mkgcs/proxy.php?url=http://resources.digicult-museen.net/dam/provided_image/m57d2ed6d1e9e5"}]]