[[{"isTitle": true, "value": "Venedig - Markusplatz"}, {"isImage": true, "value": "http://resources.digicult-museen.net/dam/provided_image/m57d2fc9597bd4"}, {"label": "Sachgruppe", "value": "Architekturfotografie"}, {"label": "Jahr", "value": "1865"}, {"label": "Ort", "value": "Venedig "}], [{"isTitle": true, "value": "Venezia - Panorama verso il Molo dall' Isola di S. Giorgio Maggiore"}, {"isImage": true, "value": "http://resources.digicult-museen.net/dam/provided_image/m57d2fc967f176"}, {"label": "Sachgruppe", "value": "Architekturfotografie"}, {"label": "Jahr", "value": "1865"}, {"label": "Ort", "value": "Venedig "}], [{"isTitle": true, "value": "Venezia - Torre e Chiesa"}, {"isImage": true, "value": "http://resources.digicult-museen.net/dam/provided_image/m57d2fc9784fc6"}, {"label": "Sachgruppe", "value": "Architekturfotografie"}, {"label": "Jahr", "value": "1865"}, {"label": "Ort", "value": "Venedig "}], [{"isTitle": true, "value": "Padua - S. Antonio"}, {"isImage": true, "value": "http://resources.digicult-museen.net/dam/provided_image/m57d2fc98551a4"}, {"label": "Sachgruppe", "value": "Architekturfotografie"}, {"label": "Jahr", "value": "1865"}, {"label": "Ort", "value": "Venedig "}], [{"isTitle": true, "value": "Venezia - Canale Grande"}, {"isImage": true, "value": "http://resources.digicult-museen.net/dam/provided_image/m57d2fc993c5cb"}, {"label": "Sachgruppe", "value": "Reisefotografie"}, {"label": "Jahr", "value": "1865"}, {"label": "Ort", "value": "Venedig "}], [{"isTitle": true, "value": "Venezia - Palazzo Pesaro"}, {"isImage": true, "value": "http://resources.digicult-museen.net/dam/provided_image/m57d2fc9a104df"}, {"label": "Sachgruppe", "value": "Reisefotografie"}, {"label": "Jahr", "value": "1865"}, {"label": "Ort", "value": "Venedig "}], [{"isTitle": true, "value": "Padua - Arenakapelle Tugenden und Laster; Iustitia und Iniustitia von Giotto"}, {"isImage": true, "value": "http://resources.digicult-museen.net/dam/provided_image/m57d2fc9b14fc8"}, {"label": "Sachgruppe", "value": "Reproduktionsfotografie"}, {"label": "Jahr", "value": "1870"}, {"label": "Ort", "value": "Venedig "}], [{"isTitle": true, "value": "Padua - Arenakapelle Tugenden und Laster; Iustitia und Iniustitia von Giotto"}, {"isImage": true, "value": "http://resources.digicult-museen.net/dam/provided_image/m57d2fc9c2c0f2"}, {"label": "Sachgruppe", "value": "Reproduktionsfotografie"}, {"label": "Jahr", "value": "1870"}, {"label": "Ort", "value": "Venedig "}], [{"isTitle": true, "value": "Padua - Arenakapelle Tugenden und Laster; Iustitia und Iniustitia von Giotto"}, {"isImage": true, "value": "http://resources.digicult-museen.net/dam/provided_image/m57d2fc9d1f0dc"}, {"label": "Sachgruppe", "value": "Reproduktionsfotografie"}, {"label": "Jahr", "value": "1870"}, {"label": "Ort", "value": "Venedig "}], [{"isTitle": true, "value": "Padua - Arenakapelle Tugenden und Laster; Iustitia und Iniustitia von Giotto"}, {"isImage": true, "value": "http://resources.digicult-museen.net/dam/provided_image/m57d2fc9deba43"}, {"label": "Sachgruppe", "value": "Reproduktionsfotografie"}, {"label": "Jahr", "value": "1870"}, {"label": "Ort", "value": "Venedig "}]]