[[{"isTitle": true, "value": "No. 1877. Tomba di Giuliano de Medici (Firenze)"}, {"label": "View item details", "isLink": true, "value": "https://google.de"}, {"isImage": true, "value": "http://resources.digicult-museen.net/dam/provided_image/m57d301c9e942b"}, {"label": "Object Number", "value": "mkg-e00135754"}, {"label": "Work Type", "value": "Fotografie"}, {"label": "Year", "value": 1902}, {"label": "Place of origin", "value": "Florenz "}], [{"isTitle": true, "value": "1939. Milano. Leonardo da Vinci"}, {"label": "View item details", "isLink": true, "value": "https://google.de"}, {"isImage": true, "value": "http://resources.digicult-museen.net/dam/provided_image/m57d301cabb6f6"}, {"label": "Object Number", "value": "mkg-e00135755"}, {"label": "Work Type", "value": "Fotografie"}, {"label": "Year", "value": 1902}, {"label": "Place of origin", "value": "Mailand "}], [{"isTitle": true, "value": "Napoli"}, {"label": "View item details", "isLink": true, "value": "https://google.de"}, {"isImage": true, "value": "http://resources.digicult-museen.net/dam/provided_image/m57d301cb9ee04"}, {"label": "Object Number", "value": "mkg-e00135756"}, {"label": "Work Type", "value": "Fotografie"}, {"label": "Year", "value": 1902}, {"label": "Place of origin", "value": "Neapel "}], [{"isTitle": true, "value": "Napoli"}, {"label": "View item details", "isLink": true, "value": "https://google.de"}, {"isImage": true, "value": "http://resources.digicult-museen.net/dam/provided_image/m57d301cc9d21e"}, {"label": "Object Number", "value": "mkg-e00135757"}, {"label": "Work Type", "value": "Fotografie"}, {"label": "Year", "value": 1902}, {"label": "Place of origin", "value": "Neapel "}], [{"isTitle": true, "value": "Verona. Tomba dei Scaligeri"}, {"label": "View item details", "isLink": true, "value": "https://google.de"}, {"isImage": true, "value": "http://resources.digicult-museen.net/dam/provided_image/m57d301cd75855"}, {"label": "Object Number", "value": "mkg-e00135761"}, {"label": "Work Type", "value": "Fotografie"}, {"label": "Year", "value": 1860}, {"label": "Place of origin", "value": "Verona "}], [{"isTitle": true, "value": "No. 1104. Marina e Hotel de Rome (Napoli)"}, {"label": "View item details", "isLink": true, "value": "https://google.de"}, {"isImage": true, "value": "http://resources.digicult-museen.net/dam/provided_image/m57d301ce4d3b3"}, {"label": "Object Number", "value": "mkg-e00135763"}, {"label": "Work Type", "value": "Fotografie"}, {"label": "Year", "value": 1860}, {"label": "Place of origin", "value": "Neapel "}], [{"isTitle": true, "value": "No. 1123. Villa Nazionale; Entrata. Napoli "}, {"label": "View item details", "isLink": true, "value": "https://google.de"}, {"isImage": true, "value": "http://resources.digicult-museen.net/dam/provided_image/m57d301cf24775"}, {"label": "Object Number", "value": "mkg-e00135767"}, {"label": "Work Type", "value": "Fotografie"}, {"label": "Year", "value": 1860}, {"label": "Place of origin", "value": "Neapel "}], [{"isTitle": true, "value": "No. 1150. Sorrento da Capo di Monte (Napoli)"}, {"label": "View item details", "isLink": true, "value": "https://google.de"}, {"isImage": true, "value": "http://resources.digicult-museen.net/dam/provided_image/m57d301cfd5447"}, {"label": "Object Number", "value": "mkg-e00135770"}, {"label": "Work Type", "value": "Fotografie"}, {"label": "Year", "value": 1860}, {"label": "Place of origin", "value": "null"}], [{"isTitle": true, "value": "No. 6100. Riviera di Chiaia (Napoli)"}, {"label": "View item details", "isLink": true, "value": "https://google.de"}, {"isImage": true, "value": "http://resources.digicult-museen.net/dam/provided_image/m57d301d08e974"}, {"label": "Object Number", "value": "mkg-e00135772"}, {"label": "Work Type", "value": "Fotografie"}, {"label": "Year", "value": 1860}, {"label": "Place of origin", "value": "Neapel "}], [{"isTitle": true, "value": "No. 1120. Riviera di Chiaia. Napoli"}, {"label": "View item details", "isLink": true, "value": "https://google.de"}, {"isImage": true, "value": "http://resources.digicult-museen.net/dam/provided_image/m57d301d14f746"}, {"label": "Object Number", "value": "mkg-e00135773"}, {"label": "Work Type", "value": "Fotografie"}, {"label": "Year", "value": 1860}, {"label": "Place of origin", "value": "Neapel "}], [{"isTitle": true, "value": "6117 Napoli - Posillipo"}, {"label": "View item details", "isLink": true, "value": "https://google.de"}, {"isImage": true, "value": "http://resources.digicult-museen.net/dam/provided_image/m57d301d20f4ff"}, {"label": "Object Number", "value": "mkg-e00135774"}, {"label": "Work Type", "value": "Fotografie"}, {"label": "Year", "value": 1860}, {"label": "Place of origin", "value": "Neapel "}]]