[[{"isTitle": true, "value": "In der Sofaecke"}, {"label": "View item details", "isLink": true, "value": "https://google.de"}, {"isImage": true, "value": "http://resources.digicult-museen.net/dam/provided_image/m5bd98d9f311e3"}, {"label": "Object Number", "value": "mkg-e00156113"}, {"label": "Work Type", "value": "Fotografie"}, {"label": "Year", "value": 1893}, {"label": "Place of origin", "value": "null"}], [{"isTitle": true, "value": "Wie sie die Treppe herunter kommt"}, {"label": "View item details", "isLink": true, "value": "https://google.de"}, {"isImage": true, "value": "http://resources.digicult-museen.net/dam/provided_image/m5bd98d9bbd113"}, {"label": "Object Number", "value": "mkg-e00156116"}, {"label": "Work Type", "value": "Fotografie"}, {"label": "Year", "value": 1893}, {"label": "Place of origin", "value": "null"}], [{"isTitle": true, "value": "Dorothy"}, {"label": "View item details", "isLink": true, "value": "https://google.de"}, {"isImage": true, "value": "http://resources.digicult-museen.net/dam/provided_image/m5bd98d9856170"}, {"label": "Object Number", "value": "mkg-e00156117"}, {"label": "Work Type", "value": "Fotografie"}, {"label": "Year", "value": 1893}, {"label": "Place of origin", "value": "null"}], [{"isTitle": true, "value": "Gitarrisierte Laute"}, {"label": "View item details", "isLink": true, "value": "https://google.de"}, {"isImage": true, "value": "http://resources.digicult-museen.net/dam/provided_image/m5a48e53f7c213"}, {"label": "Object Number", "value": "mkg-e00156119"}, {"label": "Work Type", "value": "Gitarrenlaute"}, {"label": "Year", "value": 1893}, {"label": "Place of origin", "value": "Hamburg "}], [{"isTitle": true, "value": "Break; Break on the Cold Gray Stones"}, {"label": "View item details", "isLink": true, "value": "https://google.de"}, {"isImage": true, "value": "http://resources.digicult-museen.net/dam/provided_image/m5bd98d94cc2da"}, {"label": "Object Number", "value": "mkg-e00156123"}, {"label": "Work Type", "value": "Fotografie"}, {"label": "Year", "value": 1893}, {"label": "Place of origin", "value": "Berlin "}], [{"isTitle": true, "value": "Im Schatten"}, {"label": "View item details", "isLink": true, "value": "https://google.de"}, {"isImage": true, "value": "http://resources.digicult-museen.net/dam/provided_image/m5bd98d91223df"}, {"label": "Object Number", "value": "mkg-e00156126"}, {"label": "Work Type", "value": "Fotografie"}, {"label": "Year", "value": 1893}, {"label": "Place of origin", "value": "null"}], [{"isTitle": true, "value": "Frau mit Hut "}, {"label": "View item details", "isLink": true, "value": "https://google.de"}, {"isImage": true, "value": "http://resources.digicult-museen.net/dam/provided_image/m5bd98d8d8dc04"}, {"label": "Object Number", "value": "mkg-e00156127"}, {"label": "Work Type", "value": "Fotografie"}, {"label": "Year", "value": 1893}, {"label": "Place of origin", "value": "null"}], [{"isTitle": true, "value": "Auf dem Wasserlilienteich"}, {"label": "View item details", "isLink": true, "value": "https://google.de"}, {"isImage": true, "value": "http://resources.digicult-museen.net/dam/provided_image/m5bd98d8a0ba69"}, {"label": "Object Number", "value": "mkg-e00156128"}, {"label": "Work Type", "value": "Fotografie"}, {"label": "Year", "value": 1893}, {"label": "Place of origin", "value": "null"}], [{"isTitle": true, "value": "Hausmusik"}, {"label": "View item details", "isLink": true, "value": "https://google.de"}, {"isImage": true, "value": "http://resources.digicult-museen.net/dam/provided_image/m5bd98d8675f49"}, {"label": "Object Number", "value": "mkg-e00156129"}, {"label": "Work Type", "value": "Fotografie"}, {"label": "Year", "value": 1893}, {"label": "Place of origin", "value": "null"}], [{"isTitle": true, "value": "Home; Sweet Home"}, {"label": "View item details", "isLink": true, "value": "https://google.de"}, {"isImage": true, "value": "http://resources.digicult-museen.net/dam/provided_image/m5bd98d83020bb"}, {"label": "Object Number", "value": "mkg-e00156130"}, {"label": "Work Type", "value": "Fotografie"}, {"label": "Year", "value": 1893}, {"label": "Place of origin", "value": "null"}], [{"isTitle": true, "value": "Home; sweet Home"}, {"label": "View item details", "isLink": true, "value": "https://google.de"}, {"isImage": true, "value": "http://resources.digicult-museen.net/dam/provided_image/m5bd98d7f6b376"}, {"label": "Object Number", "value": "mkg-e00156132"}, {"label": "Work Type", "value": "Fotografie"}, {"label": "Year", "value": 1893}, {"label": "Place of origin", "value": "Halle/Saale "}]]